igist
