Metadata-Version: 1.2
Name: igist
Version: 1.2.2
Summary: igist is a python package for Github gist
Home-page: https://github.com/vincent770/igist.git
Author: vinct
Author-email: vt.y@qq.com
Maintainer: vincent
Maintainer-email: vt.y@qq.com
License: MIT License
Platform: all
Classifier: License :: OSI Approved :: MIT License
Classifier: Programming Language :: Python :: 3
